LICENSE.rst
README.md
setup.cfg
setup.py
autocord/__init__.py
autocord/client.py
autocord/errors.py
autocord/op.py
autocord.egg-info/PKG-INFO
autocord.egg-info/SOURCES.txt
autocord.egg-info/dependency_links.txt
autocord.egg-info/requires.txt
autocord.egg-info/top_level.txt
autocord/types/Attachment.py
autocord/types/Deleted.py
autocord/types/DmChannel.py
autocord/types/Embed.py
autocord/types/Me.py
autocord/types/Member.py
autocord/types/Message.py
autocord/types/__init__.py