Metadata-Version: 2.1
Name: autocord
Version: 1.5.1
Summary: Discord API wrapper centered around automation
Home-page: https://github.com/wa1ker38552/autocord
Author: walker
Requires-Python: >=3.7
License-File: LICENSE.rst
